restack_composio/__init__.py
restack_composio/functions/__init__.py
restack_composio/functions/create_calendar_event.py
restack_composio/functions/get_entity.py
restack_composio/functions/get_expected_params_for_user.py
restack_composio/functions/initiate_connection.py
restack_composio/functions/is_entity_connected.py
restack_composio/service.py
restack_composio/task_queue.py
restack_composio/utils/__init__.py
restack_composio/utils/client.py
restack_composio/utils/toolsets.py
restack_composio-0.0.15.dist-info/METADATA
restack_composio-0.0.15.dist-info/WHEEL
restack_composio-0.0.15.dist-info/RECORD
